pyimdbmoviefinder/ImdbSearcher.py
pyimdbmoviefinder/JackettFetcher.py
pyimdbmoviefinder/TorrentDownloader.py
pyimdbmoviefinder/TorrentFetcher.py
pyimdbmoviefinder/TorrentSearcher.py
pyimdbmoviefinder/YtsFetcher.py
pyimdbmoviefinder/__init__.py
pyimdbmoviefinder/clisearch.py
pyimdbmoviefinder/http_utils.py
pyimdbmoviefinder/utils.py
pyimdbmoviefinder-0.1.0.dist-info/LICENSE
pyimdbmoviefinder-0.1.0.dist-info/METADATA
pyimdbmoviefinder-0.1.0.dist-info/WHEEL
pyimdbmoviefinder-0.1.0.dist-info/entry_points.txt
pyimdbmoviefinder-0.1.0.dist-info/top_level.txt
pyimdbmoviefinder-0.1.0.dist-info/RECORD
