Metadata-Version: 2.1
Name: pyimdbmoviefinder
Version: 0.1.0
Summary: Library for searching torrents that match an IMDb search.
Author-email: Vulpiculus <bastien@rnrd.ch>
Project-URL: Homepage, https://github.com/bastreynard/pyimdbmoviefinder
Project-URL: Issues, https://github.com/bastreynard/pyimdbmoviefinder/issues
Classifier: Programming Language :: Python :: 3
Classifier: License :: OSI Approved :: MIT License
Classifier: Operating System :: OS Independent
Requires-Python: >=3.8
License-File: LICENSE
Requires-Dist: requests
Requires-Dist: httplib2
Requires-Dist: cinemagoer
Requires-Dist: humanize
Requires-Dist: configparser
Requires-Dist: colorama
